{
  "name": "user",
  "datasource": "mongodb",
  "properties": {
    "name": {
      "type": "string",
      "required": true
    },
    "username": {
      "type": "string",
      "required": true
    },
    "email": {
      "type": "string",
      "required": true
    },
    "password": {
      "type": "string"
    },
    "roleId": {
      "type": "number",
      "required": true
    },
    "address": {
      "type": "string"
    },
    "waifu": {
      "type": "string"
    },
    "description": {
      "type": "string"
    },
    "image": {
      "type": "string"
    },
    "background": {
      "type": "string"
    },
    "url": {
      "type": "string"
    }
  }
}
